WebScrapeX/__init__.py
WebScrapeX/WebScrapeX.py
webscrapex-0.0.8.dist-info/METADATA
webscrapex-0.0.8.dist-info/WHEEL
webscrapex-0.0.8.dist-info/RECORD
