Metadata-Version: 2.1
Name: webscrapex
Version: 0.0.8
Summary: A unified collection of web data premises eg Apartment for sale, apartment for rent, house for sale, house for rent
Home-page: https://github.com/ILisa250/WebScrapeX
License: MIT
Keywords: WebScrapeX,web-data-extraction,web-scraping,web data collection,web data integration,web data aggregation,automated data extraction,Lisa Yvette INYANGE
Author: Lisa Yvette INYANGE
Author-email: linyange@andrew.cmu.edu
Requires-Python: >=3,<4
Classifier: License :: OSI Approved :: MIT License
Classifier: Programming Language :: Python :: 3
Classifier: Programming Language :: Python :: 3.4
Classifier: Programming Language :: Python :: 3.5
Classifier: Programming Language :: Python :: 3.6
Classifier: Programming Language :: Python :: 3.7
Classifier: Programming Language :: Python :: 3.8
Classifier: Programming Language :: Python :: 3.9
Classifier: Programming Language :: Python :: 3.10
Classifier: Programming Language :: Python :: 3.11
Project-URL: Repository, https://github.com/ILisa250/WebScrapeX
